image_manager/__init__.py
image_manager/admin.py
image_manager/models.py
image_manager/tests.py
image_manager/views.py
image_manager-0.0.2.dist-info/DESCRIPTION.rst
image_manager-0.0.2.dist-info/METADATA
image_manager-0.0.2.dist-info/metadata.json
image_manager-0.0.2.dist-info/RECORD
image_manager-0.0.2.dist-info/top_level.txt
image_manager-0.0.2.dist-info/WHEEL
