Metadata-Version: 2.0
Name: image-manager
Version: 0.0.2
Summary: django-image-manager is a no none sense image hanlding system.
Home-page: https://bitbucket.org/albertoconnor/django-builtin-password-reset
Author: Albert O'Connor
Author-email: info@albertoconnor.ca
License: UNKNOWN
Platform: UNKNOWN
Classifier: Development Status :: 3 - Alpha
Classifier: Framework :: Django
Classifier: License :: OSI Approved :: MIT License
Classifier: Operating System :: OS Independent
Classifier: Topic :: Software Development
